adesinastreets/__init__.py
adesinastreets/usa.py
adesinastreets-0.0.1.dist-info/licenses/LICENSE
adesinastreets-0.0.1.dist-info/METADATA
adesinastreets-0.0.1.dist-info/WHEEL
adesinastreets-0.0.1.dist-info/top_level.txt
adesinastreets-0.0.1.dist-info/RECORD
