Metadata-Version: 2.4
Name: adesinastreets
Version: 0.0.1
Summary: adesinastreets is a python package that gives the list of all the streets in the world offline
Author-email: Abdullah Adesina Dhikrullah <daadesina1@gmail.com>
License: Adesina license
Requires-Python: >=3.10
License-File: LICENSE
Dynamic: license-file
